{
    "finalDate": "2024-10-30",
    "day": [
        {
            "day1": [
                "WWW1WWW",
                "WWW2WWW",
                "WWW3WWW",
                "WWWW4WW",
                "WW5WWWW",
                "WWW6WWW",
                "WWW7WWWWWWWW",
                "WWWW8WsdasdasW",
                "WWWWW9asdsaWW",
                "WWWW10dasdW",
                "WWWWWWW",
                "WWWWWWW",
                "WWWWWWW",
                "WWWWWWW",
                "WWWWWWW",
                "WWWWWWW",
                "WWWWWWW",
                "WWWWWWW",
                "WWWWWWW",
                "WWWWWWW",
                "WWWWWWW"
            ],
            "day2": [
                "WWWWWWW",
                "WWWWWWW",
                "WWWWWWW",
                "WWWWWWW",
                "WWWWWWW",
                "WWWWWWW",
                "WWWWWWW",
                "WWWWWWW",
                "WWWWWWW",
                "WWWWWWW",
                "WWWWWWW",
                "WWWWWWW",
                "WWWWWWW",
                "WWWWWWW",
                "WWWWWWW",
                "WWWWWWW",
                "WWWWWWW",
                "WWWWWWW",
                "WWWWWWW",
                "WWWWWWW",
                "WWWWWWW"
            ],
            "day3": [
                "WWWWWWW",
                "WWWWWWW",
                "WWWWWWW",
                "WWWWWWW",
                "WWWWWWW",
                "WWWWWWW",
                "WWWWWWW",
                "WWWWWWW",
                "WWWWWWW",
                "WWWWWWW",
                "WWWWWWW",
                "WWWWWWW"
            ],
            "day5": [],
            "final": [
                "WWWWWWW",
                "WWWWWWW",
                "WWWWWWW",
                "WWWWWWW",
                "WWWWWWW",
                "WWWWWWW",
                "WWWWWWW",
                "WWWWWWW",
                "WWWWWWW",
                "WWWWWWW",
                "WWWWWWW",
                "WWWWWWW",
                "WWWWWWW",
                "WWWWWWW",
                "WWWWWWW",
                "WWWWWWW",
                "WWWWWWW",
                "WWWWWWW",
                "WWWWWWW",
                "WWWWWWW",
                "WWWWWWW"
            ]
        }
    ]
}